examplebtug4/__init__.py
examplebtug4/example.py
examplebtug4-0.0.1.dist-info/LICENSE.txt
examplebtug4-0.0.1.dist-info/METADATA
examplebtug4-0.0.1.dist-info/WHEEL
examplebtug4-0.0.1.dist-info/top_level.txt
examplebtug4-0.0.1.dist-info/RECORD
