Metadata-Version: 2.1
Name: examplebtug4
Version: 0.0.1
Summary: Test Project
Author: Linkin17
Author-email: author@example.com
Classifier: Programming Language :: Python :: 3
Classifier: License :: OSI Approved :: MIT License
Classifier: Operating System :: OS Independent
Requires-Python: >=3.6
License-File: LICENSE.txt
